{
  "phase": "12.0R",
  "task": "correspondence_live_proof",
  "timestamp": "2026-05-30T00:00:00Z",
  "scales": [
    {
      "scale": "UMH self-build",
      "event": "Universal Propagation Graph roadmap phase: planned → active",
      "source_node": "pgn-rp-6b51d431df",
      "affected_count": 4,
      "affected_chain": [
        "Jarvis-Level Operator Experience (depth 1)",
        "Product Projections: EOS/CreatorOS/LyfeOS (depth 2)",
        "Empyrean Studios via EOS (depth 3)",
        "Empire-Scale Leverage Infrastructure (depth 4)"
      ],
      "waves": 1,
      "status": "completed",
      "dry_run": true
    },
    {
      "scale": "Business/EOS",
      "event": "Deployment: Empyrean Studios work packet: planned → ready_for_review",
      "source_node": "pgn-wp-4a1279877f",
      "affected_count": 0,
      "waves": 0,
      "status": "completed",
      "dry_run": true,
      "note": "Work packet is orphaned (no outgoing edges). Edges form when workcells reference this packet_id. Correct behavior."
    },
    {
      "scale": "Knowledge/workflow",
      "event": "Self-build item knowledge updated",
      "source_node": "pgn-sb-1b92c688c5",
      "affected_count": 0,
      "waves": 0,
      "status": "completed",
      "dry_run": true,
      "note": "Self-build items are leaf nodes. Content opportunity links form when domain bridges exist."
    }
  ],
  "correspondence_verified": true,
  "pattern": "event → impact → plan → execute dry-run",
  "same_pattern_all_scales": true,
  "all_dry_run": true,
  "no_production_mutation": true,
  "verdict": "PASS — correspondence proof demonstrates same propagation pattern across self-build (4-depth chain), business, and knowledge scales"
}
